README.md
setup.py
gitlab_release_generator.egg-info/PKG-INFO
gitlab_release_generator.egg-info/SOURCES.txt
gitlab_release_generator.egg-info/dependency_links.txt
gitlab_release_generator.egg-info/entry_points.txt
gitlab_release_generator.egg-info/requires.txt
gitlab_release_generator.egg-info/top_level.txt
src/gitlab_release_generator/__init__.py
src/gitlab_release_generator/cli.py
src/gitlab_release_generator/version.py